debugsockets/__init__.py
debugsockets-0.8.dist-info/LICENSE
debugsockets-0.8.dist-info/METADATA
debugsockets-0.8.dist-info/WHEEL
debugsockets-0.8.dist-info/top_level.txt
debugsockets-0.8.dist-info/RECORD
