Metadata-Version: 2.1
Name: debugsockets
Version: 0.8
Summary: Advanced python sockets
Home-page: https://github.com/jinjamator/debugsockets
Author: Wilhelm Putz
Author-email: jinjamator@aci.guru
License: ASL V2
Platform: UNKNOWN
Classifier: License :: OSI Approved :: Apache Software License
Classifier: Programming Language :: Python :: 3.8
Classifier: Topic :: System :: Installation/Setup
Classifier: Topic :: System :: Systems Administration
Classifier: Topic :: Utilities
Requires-Python: >=3.8
License-File: LICENSE
